ansible_events/__init__.py
ansible_events/__main__.py
ansible_events/ansible_events.py
ansible_events/app.py
ansible_events/builtin.py
ansible_events/cli.py
ansible_events/collection.py
ansible_events/condition_parser.py
ansible_events/condition_types.py
ansible_events/conf.py
ansible_events/durability.py
ansible_events/engine.py
ansible_events/exception.py
ansible_events/inventory.py
ansible_events/key.py
ansible_events/messages.py
ansible_events/rule_generator.py
ansible_events/rule_types.py
ansible_events/rules_parser.py
ansible_events/util.py
ansible_events/websocket.py
ansible_events-0.7.0.dist-info/AUTHORS.rst
ansible_events-0.7.0.dist-info/LICENSE
ansible_events-0.7.0.dist-info/METADATA
ansible_events-0.7.0.dist-info/WHEEL
ansible_events-0.7.0.dist-info/entry_points.txt
ansible_events-0.7.0.dist-info/top_level.txt
ansible_events-0.7.0.dist-info/RECORD
