Metadata-Version: 2.1
Name: ansible-events
Version: 0.7.0
Summary: Event driven automation for Ansible
Home-page: https://github.com/benthomasson/ansible-events
Author: Ben Thomasson
Author-email: ben.thomasson@gmail.com
License: Apache-2.0
Keywords: ansible_events
Classifier: Development Status :: 2 - Pre-Alpha
Classifier: Intended Audience :: Developers
Classifier: License :: OSI Approved :: Apache Software License
Classifier: Natural Language :: English
Classifier: Programming Language :: Python :: 3
Classifier: Programming Language :: Python :: 3.6
Classifier: Programming Language :: Python :: 3.7
Classifier: Programming Language :: Python :: 3.8
Requires-Python: >=3.6
License-File: LICENSE
License-File: AUTHORS.rst
Requires-Dist: asyncio
Requires-Dist: durable-rules
Requires-Dist: pyparsing
Requires-Dist: jsonschema
Requires-Dist: jinja2
Requires-Dist: redis
Requires-Dist: dpath
Requires-Dist: janus
Requires-Dist: ansible-runner
Requires-Dist: websockets
Requires-Dist: drools-jpy
